DefuseZip/__init__.py
DefuseZip/__main__.py
DefuseZip/loader.py
DefuseZip/utils/__init__.py
DefuseZip/utils/managers.py
DefuseZip-1.0.2.dist-info/LICENSE
DefuseZip-1.0.2.dist-info/METADATA
DefuseZip-1.0.2.dist-info/WHEEL
DefuseZip-1.0.2.dist-info/entry_points.txt
DefuseZip-1.0.2.dist-info/top_level.txt
DefuseZip-1.0.2.dist-info/RECORD
