Metadata-Version: 2.1
Name: DefuseZip
Version: 1.0.2
Summary: Gathers information on a zip, mainly for seeing wether the zip could be considered malicious (Zipbomb, travelsal etc.). Work in progress.
Home-page: https://github.com/kuviokelluja/DefuseZip
Author: Tony Rintala
Author-email: rintala.tony@gmail.com
License: MIT
Requires-Python: >=3.7
License-File: LICENSE
Requires-Dist: psutil ==5.8.0
Requires-Dist: loguru <1.0.0
